Metadata-Version: 1.0
Name: matchbook
Version: 0.0.2
Summary: Matchbook API Python wrapper
Home-page: https://github.com/rozzac90/matchbook
Author: Rory Cole
Author-email: rory.cole1990@gmail.com
License: UNKNOWN
Platform: UNKNOWN
